{
  "sections": {
    "16585050139c0d3079": {
      "type": "header-skin",
      "settings": {
        "skin": "light",
        "page_header_type": "default",
        "sticky_header": false
      }
    },
    "16540668508987a87b": {
      "type": "how-we-work-hero",
      "settings": {
        "gradient": "rgba(0,0,0,0)",
        "title": "enabling circularity in fashion",
        "description": "<p>regenerated polyester made from end-of-life textiles, offering the same versatility and strength as conventional materials, at a fraction of the environmental costs<\/p>",
        "image": "shopify:\/\/shop_images\/Untitled_design-71.png",
        "image_bg": "shopify:\/\/shop_images\/tech-top-background_24f5a2d5-8ae6-422f-8d24-e1aa04bdc082.png"
      }
    },
    "165406689939d861f5": {
      "type": "how-we-work-text",
      "settings": {
        "title": "our mission is to overcome the limitations of current recycling processes in order to stop valuable materials from ending up in landfills",
        "button_title": "our materials",
        "button_link": "shopify:\/\/collections\/materials"
      }
    },
    "1657663791b1137db0": {
      "type": "how-we-work-info",
      "settings": {
        "title1": "traditional bottle to garment recycling",
        "description1": "<p>- quality of garments is influenced by the cleanliness of bottles (water intensive)<\/p><p>- quality degrades over each lifecycle <\/p><p>- no existing infrastructure to recycle the material once in garment form <\/p>",
        "title2": "Ambercycle textile to textile regeneration",
        "description2": "<p>- molecular regeneration enables high quality, durable yarn and fabric<\/p><p>- quality is maintained over each lifecycle <\/p><p>- garments can be regenerated again at end-of-life <\/p>",
        "media_type": "image",
        "image": "shopify:\/\/shop_images\/educational_graphics-3.png",
        "image_mobile": "shopify:\/\/shop_images\/educational_graphics-3.png",
        "vimeo_youtube_video": "",
        "video_file": ""
      }
    },
    "16566060495d714d08": {
      "type": "how-we-work-text",
      "disabled": true,
      "settings": {
        "title": "let's talk about circularity",
        "button_title": "",
        "button_link": ""
      }
    },
    "16540668724cb753d6": {
      "type": "how-we-work-info",
      "disabled": true,
      "settings": {
        "title1": "the problem",
        "description1": "<p>73% of clothing is landfilled or incinerated at end-of-life.<\/p><p>that's equivalent to over 120 billion garments being sent to landfill or burned for energy every year. <\/p>",
        "title2": "the solution",
        "description2": "<p>100% of cycora® material can be regenerated by Ambercycle, Inc.  into new material.<\/p><p>this eliminates 'waste' and closes the loop in fashion.<\/p>",
        "media_type": "image",
        "image": "shopify:\/\/shop_images\/poly-back.png",
        "vimeo_youtube_video": "",
        "video_file": ""
      }
    }
  },
  "order": [
    "16585050139c0d3079",
    "16540668508987a87b",
    "165406689939d861f5",
    "1657663791b1137db0",
    "16566060495d714d08",
    "16540668724cb753d6"
  ]
}